aicloud/__init__.py
aicloud/modeling/__init__.py
aicloud/modeling/training.py
aicloud/monitoring/__init__.py
aicloud/monitoring/model_monitoring.py
aicloud/plots/__init__.py
aicloud/plots/graph_plots.py
aicloud/prediction/__init__.py
aicloud/prediction/get_prediction.py
aicloud/reports/__init__.py
aicloud/reports/get_report.py
aicloud/status/__init__.py
aicloud/status/get_status.py
aicloud/users/__init__.py
aicloud/users/client.py
aicloud_lp_new-0.10.0.dist-info/METADATA
aicloud_lp_new-0.10.0.dist-info/WHEEL
aicloud_lp_new-0.10.0.dist-info/top_level.txt
aicloud_lp_new-0.10.0.dist-info/RECORD
