Metadata-Version: 2.1
Name: aicloud-lp-new
Version: 0.10.0
Requires-Dist: requests
Requires-Dist: pandas
